tox_faster/__init__.py
tox_faster/plugin.py
tox_faster-0.0.7.dist-info/LICENSE
tox_faster-0.0.7.dist-info/METADATA
tox_faster-0.0.7.dist-info/WHEEL
tox_faster-0.0.7.dist-info/entry_points.txt
tox_faster-0.0.7.dist-info/top_level.txt
tox_faster-0.0.7.dist-info/RECORD
