Metadata-Version: 2.2
Name: tox-faster
Version: 0.0.7
Summary: A tox plugin that speeds up tox a little.
Project-URL: Repository, https://github.com/hypothesis/tox-faster
Project-URL: Issues, https://github.com/hypothesis/tox-faster/issues
Project-URL: Changelog, https://github.com/hypothesis/tox-faster/releases
Classifier: Programming Language :: Python :: 3
Classifier: License :: OSI Approved :: BSD License
Classifier: Intended Audience :: Developers
Requires-Python: >=3.9
License-File: LICENSE
